aeroplatform/__init__.py
aeroplatform/cli.py
aeroplatform/config.json
aeroplatform/utils.py
aeroplatform/version.py
aeroplatform/account/__init__.py
aeroplatform/account/account.py
aeroplatform/account/commands.py
aeroplatform/configure/__init__.py
aeroplatform/configure/commands.py
aeroplatform/configure/configure.py
aeroplatform/resume/__init__.py
aeroplatform/resume/commands.py
aeroplatform/run/__init__.py
aeroplatform/run/commands.py
aeroplatform/run/run.py
aeroplatform/schedule/__init__.py
aeroplatform/schedule/commands.py
aeroplatform/schedule/schedule.py
aeroplatform-1.4.2.dist-info/LICENSE
aeroplatform-1.4.2.dist-info/METADATA
aeroplatform-1.4.2.dist-info/WHEEL
aeroplatform-1.4.2.dist-info/entry_points.txt
aeroplatform-1.4.2.dist-info/top_level.txt
aeroplatform-1.4.2.dist-info/RECORD
